odoo/addons/mrp_workorder_sequence/README.rst
odoo/addons/mrp_workorder_sequence/__init__.py
odoo/addons/mrp_workorder_sequence/__manifest__.py
odoo/addons/mrp_workorder_sequence/hooks.py
odoo/addons/mrp_workorder_sequence/i18n/it.po
odoo/addons/mrp_workorder_sequence/i18n/mrp_workorder_sequence.pot
odoo/addons/mrp_workorder_sequence/i18n/tr.po
odoo/addons/mrp_workorder_sequence/models/__init__.py
odoo/addons/mrp_workorder_sequence/models/mrp_production.py
odoo/addons/mrp_workorder_sequence/models/mrp_workorder.py
odoo/addons/mrp_workorder_sequence/readme/CONTRIBUTORS.md
odoo/addons/mrp_workorder_sequence/readme/DESCRIPTION.md
odoo/addons/mrp_workorder_sequence/readme/USAGE.md
odoo/addons/mrp_workorder_sequence/static/description/icon.png
odoo/addons/mrp_workorder_sequence/static/description/index.html
odoo/addons/mrp_workorder_sequence/tests/__init__.py
odoo/addons/mrp_workorder_sequence/tests/test_mrp_workorder_sequence.py
odoo/addons/mrp_workorder_sequence/views/mrp_workorder_view.xml
odoo_addon_mrp_workorder_sequence-17.0.1.0.0.4.dist-info/METADATA
odoo_addon_mrp_workorder_sequence-17.0.1.0.0.4.dist-info/WHEEL
odoo_addon_mrp_workorder_sequence-17.0.1.0.0.4.dist-info/top_level.txt
odoo_addon_mrp_workorder_sequence-17.0.1.0.0.4.dist-info/RECORD
